file2csv/Converter.py
file2csv/__init__.py
file2csv-1.0.0.dist-info/LICENSE
file2csv-1.0.0.dist-info/METADATA
file2csv-1.0.0.dist-info/WHEEL
file2csv-1.0.0.dist-info/top_level.txt
file2csv-1.0.0.dist-info/RECORD
