Metadata-Version: 2.1
Name: file2csv
Version: 1.0.0
Summary: Generates a fixed width file using the provided spec (offset provided in the spec file represent the length of each field).Implements a parser that can parse the fixed width file and generate a delimited file, like CSV for example.
Home-page: https://github.com/KKSanthanam/file2csv
Author: KK Santhanam
Author-email: KK.Santhanam@gmail.com
License: UNKNOWN
Project-URL: Bug Tracker, https://github.com/KKSanthanam/file2csv/issues
Platform: UNKNOWN
Classifier: Programming Language :: Python :: 3
Classifier: License :: OSI Approved :: MIT License
Classifier: Operating System :: OS Independent
Requires-Python: >=3.9
